kabas/__init__.py
kabas/_kabas_cache.py
kabas/_kabas_client.py
kabas/config.json
kabas/kabas.py
kabas/kabas_file.py
kabas/kabas_file_details.py
kabas/kabas_project.py
kabas/kabas_project_details.py
kabas/project_access_type.py
kabas-0.0.16.data/data/kabas/config.json
kabas-0.0.16.dist-info/METADATA
kabas-0.0.16.dist-info/WHEEL
kabas-0.0.16.dist-info/top_level.txt
kabas-0.0.16.dist-info/RECORD
