Metadata-Version: 2.1
Name: kabas
Version: 0.0.16
Summary: Sharing and collaboration tools for data experimentation
Home-page: UNKNOWN
Author: Pieter S.
Author-email: 
License: MIT
Platform: UNKNOWN
Classifier: License :: OSI Approved :: MIT License
Classifier: Programming Language :: Python :: 3
Classifier: Programming Language :: Python :: 3.7
Requires-Dist: requests
Requires-Dist: pandas
